ninja_tools/ReadWriteMemory.py
ninja_tools/__init__.py
ninja_tools/arduino_keyboard_mouse.py
ninja_tools/bbox.py
ninja_tools/com_ports_scan.py
ninja_tools/excel.py
ninja_tools/fast_capture.py
ninja_tools/fast_capture2.py
ninja_tools/find_image.py
ninja_tools/image_cropper.py
ninja_tools/image_finder.py
ninja_tools/image_functions.py
ninja_tools/image_processor.py
ninja_tools/inputcontrol.py
ninja_tools/json_db.py
ninja_tools/keyboard.py
ninja_tools/keycodes.py
ninja_tools/memory.py
ninja_tools/mesh.py
ninja_tools/mount.py
ninja_tools/mouse.py
ninja_tools/multiprocessing_node.py
ninja_tools/processing.py
ninja_tools/screen_capture.py
ninja_tools/sendwindow.py
ninja_tools/sort.py
ninja_tools/utils.py
ninja_tools/yolo_v5_detect.py
ninja_tools/yolov5.py
NinjaTools-0.74.dist-info/METADATA
NinjaTools-0.74.dist-info/WHEEL
NinjaTools-0.74.dist-info/top_level.txt
NinjaTools-0.74.dist-info/RECORD
