Metadata-Version: 2.1
Name: NinjaTools
Version: 0.74
Summary: Bunch of useful tools
Home-page: https://github.com/nikkoxgonzales/ninja-tools
Author: Nikko Gonzales
Author-email: nikkoxgonzales@gmail.com
License: UNKNOWN
Platform: UNKNOWN
Classifier: Programming Language :: Python :: 3
Classifier: Intended Audience :: Developers
Classifier: License :: OSI Approved :: MIT License
Classifier: Operating System :: Microsoft :: Windows
Requires-Python: >=3.7
Provides-Extra: all
Requires-Dist: opencv-python (==4.5.5.62) ; extra == 'all'
Requires-Dist: scikit-image (>=0.19.2) ; extra == 'all'
Requires-Dist: openpyxl (>=3.0.10) ; extra == 'all'
Requires-Dist: webcolors (>=1.12) ; extra == 'all'
Requires-Dist: numpy (>=1.22.3) ; extra == 'all'
Requires-Dist: Pymem (>=1.8.5) ; extra == 'all'
Requires-Dist: pywin32 (>=303) ; extra == 'all'
Requires-Dist: pyperclip (>=1.8.2) ; extra == 'all'
Requires-Dist: psutil (>=5.9.0) ; extra == 'all'
Requires-Dist: pyserial (>=3.5) ; extra == 'all'
Requires-Dist: beautifulsoup4 (>=4.11.1) ; extra == 'all'
Requires-Dist: bs4 (>=0.0.1) ; extra == 'all'
Requires-Dist: certifi (>=2022.9.24) ; extra == 'all'
Requires-Dist: charset-normalizer (>=2.1.1) ; extra == 'all'
Requires-Dist: colorama (>=0.4.6) ; extra == 'all'
Requires-Dist: idna (>=3.4) ; extra == 'all'
Requires-Dist: requests (>=2.28.1) ; extra == 'all'
Requires-Dist: soupsieve (>=2.3.2.post1) ; extra == 'all'
Requires-Dist: urllib3 (>=1.26.12) ; extra == 'all'
Requires-Dist: filterpy (>=1.4.5) ; extra == 'all'
Requires-Dist: dxcam (>=0.0.5) ; extra == 'all'
Requires-Dist: matplotlib (>=3.3) ; extra == 'all'
Requires-Dist: Pillow (>=7.1.2) ; extra == 'all'
Requires-Dist: PyYAML (>=5.3.1) ; extra == 'all'
Requires-Dist: scipy (>=1.4.1) ; extra == 'all'
Requires-Dist: thop (>=0.1.1) ; extra == 'all'
Requires-Dist: torch (>=1.7.0) ; extra == 'all'
Requires-Dist: torchvision (>=0.8.1) ; extra == 'all'
Requires-Dist: tqdm (>=4.64.0) ; extra == 'all'
Requires-Dist: tensorboard (>=2.4.1) ; extra == 'all'
Requires-Dist: pandas (>=1.1.4) ; extra == 'all'
Requires-Dist: seaborn (>=0.11.0) ; extra == 'all'
Requires-Dist: bettercam (>=1.0.0) ; extra == 'all'
Provides-Extra: excel
Requires-Dist: openpyxl (>=3.0.10) ; extra == 'excel'
Requires-Dist: webcolors (>=1.12) ; extra == 'excel'
Provides-Extra: image
Requires-Dist: opencv-python (==4.5.5.62) ; extra == 'image'
Requires-Dist: scikit-image (>=0.19.2) ; extra == 'image'
Requires-Dist: numpy (>=1.18.5) ; extra == 'image'
Provides-Extra: memory
Requires-Dist: Pymem[speed] (>=1.10.0) ; extra == 'memory'
Provides-Extra: web
Requires-Dist: beautifulsoup4 (>=4.11.1) ; extra == 'web'
Requires-Dist: bs4 (>=0.0.1) ; extra == 'web'
Requires-Dist: certifi (>=2022.9.24) ; extra == 'web'
Requires-Dist: charset-normalizer (>=2.1.1) ; extra == 'web'
Requires-Dist: colorama (>=0.4.6) ; extra == 'web'
Requires-Dist: idna (>=3.4) ; extra == 'web'
Requires-Dist: requests (>=2.28.1) ; extra == 'web'
Requires-Dist: soupsieve (>=2.3.2.post1) ; extra == 'web'
Requires-Dist: urllib3 (>=1.26.12) ; extra == 'web'
